gk6/__init__.py
gk6/cli.py
gk6/core.py
gk6-2.0.12.dist-info/LICENSE
gk6-2.0.12.dist-info/METADATA
gk6-2.0.12.dist-info/WHEEL
gk6-2.0.12.dist-info/entry_points.txt
gk6-2.0.12.dist-info/RECORD
