Metadata-Version: 2.3
Name: gk6
Version: 2.0.12
Summary: Postman to k6 converter
License: MIT
Keywords: postman,k6,converter
Author: Gopi Krishna
Author-email: gopikrishna4595@gmail.com
Requires-Python: >=3.9,<4.0
Classifier: License :: OSI Approved :: MIT License
Classifier: Programming Language :: Python :: 3
Classifier: Programming Language :: Python :: 3.9
Classifier: Programming Language :: Python :: 3.10
Classifier: Programming Language :: Python :: 3.11
Classifier: Programming Language :: Python :: 3.12
Classifier: Programming Language :: Python :: 3.13
Requires-Dist: typer (>=0.16.0,<0.17.0)
Project-URL: Documentation, https://gopikrishna4595.github.io/gk6/
Project-URL: Homepage, https://github.com/gopikrishna4595/gk6
Project-URL: Repository, https://github.com/gopikrishna4595/gk6
